[      


            {
    "id": "139",
    "nombre": "Bandeja con forma de pato de metal",
    "imagen": "compressed/139-1.JPG",
    "categorias": [ "decoracion", "vintage", "raro", "cocina"],
    "precio": 25,
    "url": "/139"
  },



           {
    "id": "37",
    "nombre": "Lámpara bola vintage",
    "imagen": "compressed/37-1.JPG",
    "categorias": ["iluminacion", "decoracion", "vintage", "dormitorio", "salon", "bano", "cocina"],
    "precio": 50,
    "url": "/37"
  },

          {
    "id": "102",
    "nombre": "Ikebana de vidrio ahumado vintage",
    "imagen": "compressed/102-2.JPG",
    "categorias": [ "decoracion", "vintage", "dormitorio", "salon"],
    "precio": 23,
    "url": "/102"
  },

             {
    "id": "89",
    "nombre": "Lámpara de escritorio roja años 70",
    "imagen": "compressed/89-1.JPG",
    "categorias": ["iluminacion", "decoracion", "vintage", "dormitorio", "salon", "bano", "cocina"],
    "precio": 50,
    "url": "/89"
  },
 
                {
    "id": "112",
    "nombre": "Portalápices giratorio Y2K",
    "imagen": "compressed/112-3.JPG",
    "categorias": ["herramienta", "vintage", "decoracion", "oficina", "organizacion", "almacenaje"],
    "precio": 15,
    "url": "/112"
  },

{
    "id": "113",
    "nombre": "Lámpara de escritorio Memphis style 1990",
    "imagen": "compressed/113-5.JPG",
    "categorias": ["iluminacion", "decoracion", "vintage", "dormitorio", "salon", "oficina"],
    "precio": 68,
    "url": "113"
  },


          {
    "id": "104",
    "nombre": "Bandeja Inoxal",
    "imagen": "compressed/104-5.JPG",
    "categorias": ["cocina", "herramienta", "almacenaje", "vintage"],
    "precio": 26,
    "url": "/104"
  },




                    {
    "id": "98",
    "nombre": "Pack Spoonforks de Viners",
    "imagen": "compressed/98-5.JPG",
    "categorias": ["vintage","herramienta", "cocina", "raro", "diseno"],
    "precio": 16,
    "url": "/98"
  },


          {
    "id": "93",
    "nombre": "Lámpara de enchufe blanca Vintage",
    "imagen": "compressed/93-12.JPG",
    "categorias": ["iluminacion", "decoracion", "vintage", "dormitorio", "salon", "bano", "cocina"],
    "precio": 59,
    "url": "/93"
  },
            {
    "id": "101",
    "nombre": "Juego de letras Vintage Kiddicraft años 50",
    "imagen": "compressed/101-4.JPG",
    "categorias": ["vintage","raro"],
    "precio": 38,
    "url": "/101"
  },


                  {
    "id": "94",
    "nombre": "Libro Rupert The Daily Express Annual 1975",
    "imagen": "compressed/94-1.JPG",
    "categorias": ["vintage","raro", "print"],
    "precio": 17,
    "url": "/94"
  },

        {
    "id": "68",
    "nombre": "Lámpara orientable de pared amarilla y azul",
    "imagen": "compressed/68-15.JPG",
    "categorias": ["iluminacion", "decoracion", "vintage", "dormitorio", "salon", "bano", "cocina"],
    "precio": 50,
    "url": "/68"
  },





      {
    "id": "26",
    "nombre": "Lámpara de pared orientable IKEA Lod 1990",
    "imagen": "compressed/26-5.JPG",
    "categorias": ["iluminacion", "decoracion", "vintage", "dormitorio", "salon", "bano", "cocina"],
    "precio": 50,
    "url": "/26"
  },
          {
    "id": "59",
    "nombre": "Dos candelabros IKEA Renös",
    "imagen": "compressed/59-1.JPG",
    "categorias": ["iluminacion", "decoracion", "dormitorio", "salon", "bano", "cocina", "herramienta"],
    "precio": 40,
    "url": "/59"
  },


  {
    "id": "pressers",
    "nombre": "Trío transfers adhesivos Vintage",
    "imagen": "compressed/pressers4.JPG",
    "categorias": ["cocina", "organizacion", "almacenaje", "vintage"],
    "precio": 12,
    "url": "/pressers"
  },
    {
    "id": "castel",
    "nombre": "Bandeja organizadora giratoria Vintage",
    "imagen": "compressed/castel3.JPG",
    "categorias": ["cocina", "organizacion", "almacenaje", "vintage"],
    "precio": 18,
    "url": "/castel"
  },

    {
    "id": "sacapuntas",
    "nombre": "Sacapuntas Transbordador Espacial Columbia años 80",
    "imagen": "compressed/sacapuntas2.JPG",
    "categorias": ["raro", "herramienta", "vintage"],
    "precio": 12,
    "url": "/sacapuntas"
  },

    {
    "id": "platosracion",
    "nombre": "Set de 2 platos de raciones de cerámica",
    "imagen": "compressed/IMG_4203.JPG",
    "categorias": ["cocina", "herramienta", "vintage"],
    "precio": 20,
    "url": "/platosracion"
  },

  {
    "id": "payasos",
    "nombre": "Sujetalibros con forma de payaso",
    "imagen": "compressed/IMG_2743.JPG",
    "categorias": ["decoracion", "dormitorio", "organizacion"],
    "precio": 20,
    "url": "/payasos"
  },

  {
    "id": "bolsoverde",
    "nombre": "Bolso verde años 70",
    "imagen": "compressed/IMG_1872.JPG",
    "categorias": ["textil", "vintage"],
    "precio": 25,
    "url": "/bolsoverde"
  },

  {
    "id": "percherosylablanco",
    "nombre": "Perchero Syla blanco años 70",
    "imagen": "compressed/IMG_7634.jpg",
    "categorias": ["vintage", "almacenaje", "dormitorio", "oficina", "bano"],
    "precio": 28,
    "url": "/percherosylablanco"
  },


  {
    "id": "palas",
    "nombre": "Juego de palas de playa",
    "imagen": "compressed/IMG_7984.JPG",
    "categorias": ["outdoor", "vintage"],
    "precio": 15,
    "url": "/palas"
  },
  {
    "id": "teteramarron",
    "nombre": "Tetera marrón de cerámica",
    "imagen": "compressed/IMG_7505.JPG",
    "categorias": ["cocina", "vintage"],
    "precio": 25,
    "url": "/teteramarron"
  },
  {
    "id": "servilletero",
    "nombre": "Servilletero rojo años 80",
    "imagen": "compressed/IMG_7195.JPG",
    "categorias": ["cocina", "decoracion", "vintage"],
    "precio": 22,
    "url": "/servilletero"
  },
  {
    "id": "prensaajos",
    "nombre": "Prensa ajos - deshuesador",
    "imagen": "compressed/IMG_7214 2.JPG",
    "categorias": ["herramienta", "cocina", "vintage"],
    "precio": 20,
    "url": "/prensaajos"
  },


  {
    "id": "picahierbas",
    "nombre": "Picahierbas manual",
    "imagen": "compressed/IMG_2825.jpg",
    "categorias": ["cocina", "herramienta"],
    "precio": 20,
    "url": "/picahierbas"
  },

  {
    "id": "tazasamarillas",
    "nombre": "Set de dos tazas 70s",
    "imagen": "compressed/IMG_2986.jpg",
    "categorias": ["cocina", "vintage"],
    "precio": 12,
    "url": "/tazasamarillas"
  },
  {
    "id": "bascularedonda",
    "nombre": "Báscula mecánica redonda",
    "imagen": "compressed/IMG_2922.jpg",
    "categorias": ["herramienta","cocina"],
    "precio": 28,
    "url": "/bascularedonda"
  },
  {
    "id": "libreta",
    "nombre": "Libreta de direcciones antigua",
    "imagen": "compressed/IMG_2796.jpg",
    "categorias": ["vintage", "oficina", "organizacion"],
    "precio": 15,
    "url": "/libreta"
  },
  {
    "id": "baño",
    "nombre": "Set de 2 jaboneras de pared",
    "imagen": "compressed/IMG_2844.jpg",
    "categorias": ["almacenaje", "bano"],
    "precio": 30,
    "url": "/baño"
  },
  {
    "id": "tazaancha",
    "nombre": "Taza de cerámica",
    "imagen": "compressed/IMG_2453.jpg",
    "categorias": ["cocina"],
    "precio": 8,
    "url": "/tazaancha"
  },
  {
    "id": "tresbolas",
    "nombre": "Florero tres bolas",
    "imagen": "compressed/IMG_2425.jpg",
    "categorias": ["decoracion"],
    "precio": 15,
    "url": "/tresbolas"
  },
  {
    "id": "bolmarron",
    "nombre": "Bol de cerámica con gradiente",
    "imagen": "compressed/IMG_2140.jpg",
    "categorias": ["cocina"],
    "precio": 21,
    "url": "/bolmarron"
  },
  {
    "id": "tarrooso",
    "nombre": "Tarro cerámica oso 60-70s",
    "imagen": "compressed/IMG_1427.JPG",
    "categorias": ["cocina", "almacenaje", "vintage", "raro"],
    "precio": 25,
    "url": "/tarrooso"
  },
  {
    "id": "candelabrohierro",
    "nombre": "Candelabro de hierro en espiral",
    "imagen": "compressed/IMG_1418.JPG",
    "categorias": ["vintage", "decoracion"],
    "precio": 21,
    "url": "/candelabrohierro"
  },
  {
    "id": "triocopasvidrio",
    "nombre": "Trío copas Crisal Glass",
    "imagen": "compressed/IMG_1472.JPG",
    "categorias": ["cocina"],
    "precio": 15,
    "url": "/triocopasvidrio"
  },
  {
    "id": "exprimidorrojo",
    "nombre": "Exprimidor con ventosa años 70",
    "imagen": "compressed/IMG_1468.JPG",
    "categorias": ["cocina", "herramienta", "vintage"],
    "precio": 21,
    "url": "/exprimidorrojo"
  },
  {
    "id": "jarrapyrex",
    "nombre": "Jarra Pyrex vintage",
    "imagen": "compressed/IMG_1146.jpg",
    "categorias": ["cocina", "herramienta", "decoracion"],
    "precio": 23,
    "url": "/jarrapyrex"
  },


  {
    "id": "dadolapiz",
    "nombre": "Dado portalápices de cerámica",
    "imagen": "compressed/IMG_0444.jpg",
    "categorias": ["decoracion", "vintage", "raro", "oficina", "almacenaje", "organizacion"],
    "precio": 20,
    "url": "/dadolapiz"
  },

  {
    "id": "barracocina",
    "nombre": "Barra organizadora vintage",
    "imagen": "compressed/IMG_0067.jpg",
    "categorias": ["cocina", "bano", "almacenaje", "organizacion"],
    "precio": 18,
    "url": "/barracocina"
  },
  {
    "id": "spaghetti",
    "nombre": "Medidor-servidor spaghetti",
    "imagen": "compressed/IMG_9870 (1).jpg",
    "categorias": ["cocina", "herramienta"],
    "precio": 10,
    "url": "/spaghetti"
  },
  {
    "id": "posavasoscristal",
    "nombre": "Set de 4 posavasos de cristal",
    "imagen": "compressed/IMG_9407.jpg",
    "categorias": ["cocina", "salon", "decoracion"],
    "precio": 16,
    "url": "/posavasoscristal"
  },
  {
    "id": "saleroypimentero",
    "nombre": "Set salero y pimentero",
    "imagen": "compressed/IMG_8836.jpg",
    "categorias": ["cocina", "herramienta", "decoracion"],
    "precio": 8,
    "url": "/saleroypimentero"
  },

  {
    "id": "bowmaker",
    "nombre": "Bow Maker",
    "imagen": "compressed/IMG_7951.jpg",
    "categorias": ["herramienta", "raro"],
    "precio": 5,
    "url": "/bowmaker"
  },
  {
    "id": "bagsealer",
    "nombre": "Bag Sealer",
    "imagen": "compressed/IMG_7982.jpg",
    "categorias": ["herramienta", "vintage", "raro"],
    "precio": 8,
    "url": "/bagsealer"
  },
  {
    "id": "tijerasanimales",
    "nombre": "Tijeras de animales",
    "imagen": "compressed/IMG_7667.jpg",
    "categorias": ["herramienta"],
    "precio": 3,
    "url": "/tijerasanimales"
  },

  {
    "id": "abrebotellas",
    "nombre": "Abrebotellas de acero",
    "imagen": "compressed/IMG_6691.jpg",
    "categorias": ["herramienta", "cocina"],
    "precio": 7,
    "url": "/abrebotellas"
  },
  {
    "id": "toca",
    "nombre": "Escoba portugesa",
    "imagen": "compressed/IMG_6661.jpg",
    "categorias": ["herramienta"],
    "precio": 15,
    "url": "/toca"
  },

  {
    "id": "salsera",
    "nombre": "Salsera de porcelana",
    "imagen": "compressed/IMG_5309.jpg",
    "categorias": ["herramienta", "cocina", "vintage"],
    "precio": 25,
    "url": "/salsera"
  },
  {
    "id": "ralladorqueso",
    "nombre": "Rallador de queso",
    "imagen": "compressed/IMG_5545.jpg",
    "categorias": ["herramienta", "cocina"],
    "precio": 16,
    "url": "/ralladorqueso"
  },
  {
    "id": "cartaceleste",
    "nombre": "Carta celeste 1976",
    "imagen": "compressed/IMG_5056.jpg",
    "categorias": ["raro", "vintage", "print"],
    "precio": 14,
    "url": "/cartaceleste"
  },

  {
    "id": "llaveroelf",
    "nombre": "Llavero Elf con metro",
    "imagen": "compressed/IMG_4887.jpg",
    "categorias": ["raro"],
    "precio": 8,
    "url": "/llaveroelf"
  },
  {
    "id": "partager",
    "nombre": "Plantillas para cortar tartas",
    "imagen": "compressed/IMG_2516.jpg",
    "categorias": ["herramienta", "cocina", "vintage"],
    "precio": 5,
    "url": "/partager"
  },
  {
    "id": "perchagris",
    "nombre": "Percha metálica para pantalones",
    "imagen": "compressed/IMG_1538.jpg",
    "categorias": ["organizacion", "almacenaje", "dormitorio"],
    "precio": 6,
    "url": "/perchagris"
  },
  {
    "id": "babymobil",
    "nombre": "Baby mobile de animales",
    "imagen": "compressed/IMG_3860 copia.jpg",
    "categorias": [],
    "precio": 25,
    "url": "/babymobil"
  }
]


